Metadata-Version: 1.0
Name: char-count
Version: 0.1
Summary: Number of characters in file
Home-page: UNKNOWN
Author: UNKNOWN
Author-email: i.m.demyanov@gmail.com
License: UNKNOWN
Platform: UNKNOWN
